nix_utils/__init__.py
nix_utils/misc_utils.py
nix_utils/net_utils.py
nix_utils/os_utils.py
nix_utils/pip_utils.py
nix_utils/pkg_utils.py
nix_utils-1.3.8.dist-info/licenses/LICENSE
nix_utils-1.3.8.dist-info/METADATA
nix_utils-1.3.8.dist-info/WHEEL
nix_utils-1.3.8.dist-info/top_level.txt
nix_utils-1.3.8.dist-info/RECORD
