Metadata-Version: 2.4
Name: nix-utils
Version: 1.3.8
Summary: nix-utils
Home-page: https://github.com/neodyme-labs/nix-utilities
Download-URL: https://github.com/neodyme-labs/nix-utilities
Author: Daniel K
Author-email: dkilimnik@neodymetechnologies.com
License: GNU
Project-URL: Documentation, https://github.com/neodyme-labs/nix-utilities
Platform: Linux
License-File: LICENSE
Requires-Dist: pycryptodomex
Requires-Dist: pip
Requires-Dist: cloud-ds-api
Requires-Dist: img-splicer
Dynamic: author
Dynamic: author-email
Dynamic: description
Dynamic: description-content-type
Dynamic: download-url
Dynamic: home-page
Dynamic: license
Dynamic: license-file
Dynamic: platform
Dynamic: project-url
Dynamic: requires-dist
Dynamic: summary
